LICENCE.txt
MANIFEST.in
README.rst
setup.py
emencia_django_forum.egg-info/PKG-INFO
emencia_django_forum.egg-info/SOURCES.txt
emencia_django_forum.egg-info/dependency_links.txt
emencia_django_forum.egg-info/not-zip-safe
emencia_django_forum.egg-info/requires.txt
emencia_django_forum.egg-info/top_level.txt
forum/__init__.py
forum/admin.py
forum/crumbs.py
forum/markup.py
forum/mixins.py
forum/models.py
forum/settings.py
forum/signals.py
forum/urls.py
forum/forms/__init__.py
forum/forms/category.py
forum/forms/crispies.py
forum/forms/post.py
forum/forms/thread.py
forum/locale/fr/LC_MESSAGES/django.mo
forum/locale/fr/LC_MESSAGES/django.po
forum/migrations/0001_initial.py
forum/migrations/__init__.py
forum/static/css/forum_app.css
forum/static/fonts/forum.eot
forum/static/fonts/forum.svg
forum/static/fonts/forum.ttf
forum/static/fonts/forum.woff
forum/templates/403.html
forum/templates/forum/base.html
forum/templates/forum/pagination.html
forum/templates/forum/subbase.html
forum/templates/forum/author/_vcard.html
forum/templates/forum/category/details.html
forum/templates/forum/category/form.html
forum/templates/forum/category/index.html
forum/templates/forum/markup/_text_field_djangocodemirror_js.html
forum/templates/forum/markup/_text_markup_render.html
forum/templates/forum/post/delete_form.html
forum/templates/forum/post/form.html
forum/templates/forum/thread/details.html
forum/templates/forum/thread/form.html
forum/templates/forum/thread/generic_index.html
forum/templates/forum/thread/lasts.html
forum/templates/forum/thread/widget_announces.html
forum/templates/forum/threadwatch/email_content.txt
forum/templates/forum/threadwatch/email_subject.txt
forum/templatetags/__init__.py
forum/templatetags/forum_markup.py
forum/templatetags/forum_tags.py
forum/utils/__init__.py
forum/utils/imports.py
forum/utils/views.py
forum/views/__init__.py
forum/views/category.py
forum/views/index.py
forum/views/post.py
forum/views/thread.py